{"updated_at":"2026-06-28T03:11:15Z","race_date":"2026-06-28","exhibition":[{"race_stadium_number":5,"race_number":1,"boats":[{"racer_boat_number":1,"ex_time":6.77,"lap_time":36.4,"turn_time":5.8,"straight_time":6.8},{"racer_boat_number":2,"ex_time":6.84,"lap_time":37.26,"turn_time":6.27,"straight_time":6.83},{"racer_boat_number":3,"ex_time":6.83,"lap_time":37.09,"turn_time":6.05,"straight_time":6.9},{"racer_boat_number":4,"ex_time":6.76,"lap_time":37.44,"turn_time":5.79,"straight_time":7.17},{"racer_boat_number":5,"ex_time":6.78,"lap_time":37.33,"turn_time":5.87,"straight_time":7.1},{"racer_boat_number":6,"ex_time":6.76,"lap_time":37.13,"turn_time":5.68,"straight_time":7.07}]},{"race_stadium_number":5,"race_number":2,"boats":[{"racer_boat_number":1,"ex_time":6.8,"lap_time":37.54,"turn_time":5.79,"straight_time":7.03},{"racer_boat_number":2,"ex_time":6.82,"lap_time":37.7,"turn_time":6.19,"straight_time":6.93},{"racer_boat_number":3,"ex_time":6.75,"lap_time":37.2,"turn_time":5.96,"straight_time":7.0},{"racer_boat_number":4,"ex_time":6.75,"lap_time":38.62,"turn_time":5.75,"straight_time":7.33},{"racer_boat_number":5,"ex_time":6.74,"lap_time":37.72,"turn_time":5.71,"straight_time":7.1},{"racer_boat_number":6,"ex_time":6.8,"lap_time":37.87,"turn_time":5.68,"straight_time":7.13}]},{"race_stadium_number":10,"race_number":1,"boats":[{"racer_boat_number":1,"lap_time":37.17,"turn_time":5.7,"straight_time":6.87,"ex_time":0.0},{"racer_boat_number":2,"lap_time":37.83,"turn_time":6.08,"straight_time":6.9,"ex_time":0.0},{"racer_boat_number":3,"lap_time":38.02,"turn_time":6.1,"straight_time":7.03,"ex_time":0.0},{"racer_boat_number":4,"lap_time":37.47,"turn_time":5.83,"straight_time":6.88,"ex_time":0.0},{"racer_boat_number":5,"lap_time":37.8,"turn_time":6.08,"straight_time":6.8,"ex_time":0.0},{"racer_boat_number":6,"lap_time":38.58,"turn_time":6.47,"straight_time":6.92,"ex_time":0.0}]},{"race_stadium_number":10,"race_number":2,"boats":[{"racer_boat_number":1,"lap_time":37.27,"turn_time":5.67,"straight_time":6.82,"ex_time":0.0},{"racer_boat_number":2,"lap_time":37.23,"turn_time":6.0,"straight_time":6.72,"ex_time":0.0},{"racer_boat_number":3,"lap_time":37.95,"turn_time":6.1,"straight_time":6.8,"ex_time":0.0},{"racer_boat_number":4,"lap_time":37.55,"turn_time":5.78,"straight_time":6.82,"ex_time":0.0},{"racer_boat_number":5,"lap_time":37.52,"turn_time":5.67,"straight_time":6.73,"ex_time":0.0},{"racer_boat_number":6,"lap_time":37.85,"turn_time":5.92,"straight_time":6.88,"ex_time":0.0}]},{"race_stadium_number":10,"race_number":3,"boats":[{"racer_boat_number":1,"lap_time":37.38,"turn_time":5.62,"straight_time":6.78,"ex_time":0.0},{"racer_boat_number":2,"lap_time":37.15,"turn_time":5.57,"straight_time":6.88,"ex_time":0.0},{"racer_boat_number":3,"lap_time":37.48,"turn_time":5.72,"straight_time":6.92,"ex_time":0.0},{"racer_boat_number":4,"lap_time":37.98,"turn_time":6.05,"straight_time":6.85,"ex_time":0.0},{"racer_boat_number":5,"lap_time":37.23,"turn_time":5.82,"straight_time":6.78,"ex_time":0.0},{"racer_boat_number":6,"lap_time":37.4,"turn_time":5.7,"straight_time":6.87,"ex_time":0.0}]},{"race_stadium_number":10,"race_number":4,"boats":[{"racer_boat_number":1,"lap_time":36.95,"turn_time":5.92,"straight_time":6.7,"ex_time":0.0},{"racer_boat_number":2,"lap_time":37.65,"turn_time":6.28,"straight_time":6.62,"ex_time":0.0},{"racer_boat_number":3,"lap_time":37.4,"turn_time":5.78,"straight_time":6.87,"ex_time":0.0},{"racer_boat_number":4,"lap_time":37.87,"turn_time":6.05,"straight_time":6.82,"ex_time":0.0},{"racer_boat_number":5,"lap_time":37.6,"turn_time":5.85,"straight_time":6.73,"ex_time":0.0},{"racer_boat_number":6,"lap_time":37.3,"turn_time":5.95,"straight_time":6.72,"ex_time":0.0}]},{"race_stadium_number":10,"race_number":5,"boats":[{"racer_boat_number":1,"lap_time":37.78,"turn_time":5.95,"straight_time":6.83,"ex_time":0.0},{"racer_boat_number":2,"lap_time":37.9,"turn_time":5.98,"straight_time":6.75,"ex_time":0.0},{"racer_boat_number":3,"lap_time":38.03,"turn_time":5.93,"straight_time":6.87,"ex_time":0.0},{"racer_boat_number":4,"lap_time":37.65,"turn_time":5.88,"straight_time":6.98,"ex_time":0.0},{"racer_boat_number":5,"lap_time":38.02,"turn_time":5.98,"straight_time":6.93,"ex_time":0.0},{"racer_boat_number":6,"lap_time":37.92,"turn_time":5.98,"straight_time":7.02,"ex_time":0.0}]},{"race_stadium_number":10,"race_number":6,"boats":[{"racer_boat_number":1,"lap_time":37.13,"turn_time":5.57,"straight_time":6.9,"ex_time":0.0},{"racer_boat_number":2,"lap_time":36.88,"turn_time":5.58,"straight_time":6.8,"ex_time":0.0},{"racer_boat_number":3,"lap_time":37.2,"turn_time":5.73,"straight_time":6.78,"ex_time":0.0},{"racer_boat_number":4,"lap_time":37.47,"turn_time":5.85,"straight_time":6.75,"ex_time":0.0},{"racer_boat_number":5,"lap_time":37.47,"turn_time":5.73,"straight_time":6.83,"ex_time":0.0},{"racer_boat_number":6,"lap_time":38.22,"turn_time":5.92,"straight_time":6.8,"ex_time":0.0}]},{"race_stadium_number":10,"race_number":7,"boats":[{"racer_boat_number":1,"lap_time":37.32,"turn_time":5.7,"straight_time":6.82,"ex_time":0.0},{"racer_boat_number":2,"lap_time":37.55,"turn_time":5.83,"straight_time":6.78,"ex_time":0.0},{"racer_boat_number":3,"lap_time":37.65,"turn_time":5.88,"straight_time":6.85,"ex_time":0.0},{"racer_boat_number":4,"lap_time":36.92,"turn_time":5.55,"straight_time":6.83,"ex_time":0.0},{"racer_boat_number":5,"lap_time":37.65,"turn_time":5.8,"straight_time":6.92,"ex_time":0.0},{"racer_boat_number":6,"lap_time":38.68,"turn_time":6.38,"straight_time":6.88,"ex_time":0.0}]},{"race_stadium_number":10,"race_number":8,"boats":[{"racer_boat_number":1,"lap_time":37.72,"turn_time":5.67,"straight_time":6.85,"ex_time":0.0},{"racer_boat_number":2,"lap_time":37.85,"turn_time":6.12,"straight_time":6.83,"ex_time":0.0},{"racer_boat_number":3,"lap_time":37.92,"turn_time":6.17,"straight_time":6.88,"ex_time":0.0},{"racer_boat_number":4,"lap_time":37.53,"turn_time":5.85,"straight_time":6.9,"ex_time":0.0},{"racer_boat_number":5,"lap_time":37.13,"turn_time":5.68,"straight_time":6.8,"ex_time":0.0},{"racer_boat_number":6,"lap_time":37.47,"turn_time":5.9,"straight_time":6.88,"ex_time":0.0}]},{"race_stadium_number":10,"race_number":9,"boats":[{"racer_boat_number":1,"lap_time":37.82,"turn_time":5.9,"straight_time":6.93,"ex_time":0.0},{"racer_boat_number":2,"lap_time":37.1,"turn_time":5.73,"straight_time":6.83,"ex_time":0.0},{"racer_boat_number":3,"lap_time":37.43,"turn_time":5.77,"straight_time":6.92,"ex_time":0.0},{"racer_boat_number":4,"lap_time":37.97,"turn_time":5.78,"straight_time":7.0,"ex_time":0.0},{"racer_boat_number":5,"lap_time":38.42,"turn_time":6.13,"straight_time":6.88,"ex_time":0.0},{"racer_boat_number":6,"lap_time":38.07,"turn_time":6.0,"straight_time":6.92,"ex_time":0.0}]},{"race_stadium_number":14,"race_number":1,"boats":[{"racer_boat_number":1,"ex_time":6.8,"lap_time":36.34,"turn_time":5.66,"straight_time":6.98},{"racer_boat_number":2,"ex_time":6.85,"lap_time":36.6,"turn_time":5.67,"straight_time":7.13},{"racer_boat_number":3,"ex_time":6.94,"lap_time":37.34,"turn_time":5.86,"straight_time":7.17},{"racer_boat_number":4,"ex_time":6.9,"lap_time":37.27,"turn_time":5.93,"straight_time":7.1},{"racer_boat_number":5,"ex_time":6.91,"lap_time":36.83,"turn_time":5.94,"straight_time":7.07},{"racer_boat_number":6,"ex_time":6.83,"lap_time":36.57,"turn_time":5.9,"straight_time":7.2}]},{"race_stadium_number":14,"race_number":2,"boats":[{"racer_boat_number":1,"ex_time":6.77,"lap_time":37.05,"turn_time":5.62,"straight_time":7.2},{"racer_boat_number":2,"ex_time":6.95,"lap_time":36.63,"turn_time":5.43,"straight_time":7.23},{"racer_boat_number":3,"ex_time":6.99,"lap_time":37.03,"turn_time":5.5,"straight_time":7.23},{"racer_boat_number":4,"ex_time":6.95,"lap_time":37.33,"turn_time":6.0,"straight_time":7.2},{"racer_boat_number":5,"ex_time":6.95,"lap_time":37.09,"turn_time":5.93,"straight_time":7.3},{"racer_boat_number":6,"ex_time":6.87,"lap_time":36.8,"turn_time":5.6,"straight_time":7.17}]},{"race_stadium_number":14,"race_number":3,"boats":[{"racer_boat_number":1,"ex_time":6.79,"lap_time":35.97,"turn_time":5.5,"straight_time":6.93},{"racer_boat_number":2,"ex_time":6.9,"lap_time":36.67,"turn_time":5.57,"straight_time":6.99},{"racer_boat_number":3,"ex_time":6.92,"lap_time":36.9,"turn_time":5.5,"straight_time":7.07},{"racer_boat_number":4,"ex_time":6.91,"lap_time":36.83,"turn_time":5.63,"straight_time":7.03},{"racer_boat_number":5,"ex_time":6.86,"lap_time":37.34,"turn_time":6.36,"straight_time":6.87},{"racer_boat_number":6,"ex_time":6.96,"lap_time":36.82,"turn_time":6.29,"straight_time":6.93}]},{"race_stadium_number":14,"race_number":4,"boats":[{"racer_boat_number":1,"ex_time":6.77,"lap_time":36.08,"turn_time":5.96,"straight_time":6.93},{"racer_boat_number":2,"ex_time":6.86,"lap_time":36.73,"turn_time":5.87,"straight_time":7.28},{"racer_boat_number":3,"ex_time":6.83,"lap_time":36.63,"turn_time":5.7,"straight_time":7.1},{"racer_boat_number":4,"ex_time":6.87,"lap_time":36.74,"turn_time":5.67,"straight_time":7.1},{"racer_boat_number":5,"ex_time":6.9,"lap_time":36.97,"turn_time":5.7,"straight_time":7.25},{"racer_boat_number":6,"ex_time":6.9,"lap_time":37.23,"turn_time":5.73,"straight_time":7.23}]},{"race_stadium_number":21,"race_number":1,"boats":[{"racer_boat_number":1,"ex_time":6.73,"lap_time":36.3,"turn_time":7.74,"straight_time":7.69},{"racer_boat_number":2,"ex_time":6.84,"lap_time":36.86,"turn_time":7.83,"straight_time":7.66},{"racer_boat_number":3,"ex_time":6.79,"lap_time":36.79,"turn_time":7.8,"straight_time":7.75},{"racer_boat_number":4,"ex_time":6.81,"lap_time":36.79,"turn_time":7.86,"straight_time":7.67},{"racer_boat_number":5,"ex_time":6.81,"lap_time":36.97,"turn_time":7.65,"straight_time":7.8},{"racer_boat_number":6,"ex_time":6.81,"lap_time":37.32,"turn_time":8.17,"straight_time":7.71}]},{"race_stadium_number":21,"race_number":2,"boats":[{"racer_boat_number":1,"ex_time":6.79,"lap_time":36.61,"turn_time":7.76,"straight_time":7.66},{"racer_boat_number":2,"ex_time":6.73,"lap_time":37.03,"turn_time":8.03,"straight_time":7.69},{"racer_boat_number":3,"ex_time":6.74,"lap_time":37.11,"turn_time":7.76,"straight_time":7.73},{"racer_boat_number":4,"ex_time":6.71,"lap_time":37.04,"turn_time":8.06,"straight_time":7.69},{"racer_boat_number":5,"ex_time":6.73,"lap_time":37.11,"turn_time":7.9,"straight_time":7.67},{"racer_boat_number":6,"ex_time":6.68,"lap_time":37.0,"turn_time":8.02,"straight_time":7.71}]},{"race_stadium_number":21,"race_number":3,"boats":[{"racer_boat_number":1,"ex_time":6.81,"lap_time":36.71,"turn_time":7.84,"straight_time":7.76},{"racer_boat_number":2,"ex_time":6.85,"lap_time":36.78,"turn_time":7.89,"straight_time":7.72},{"racer_boat_number":3,"ex_time":6.8,"lap_time":37.34,"turn_time":7.91,"straight_time":7.79},{"racer_boat_number":4,"ex_time":6.82,"lap_time":36.93,"turn_time":7.75,"straight_time":7.74},{"racer_boat_number":5,"ex_time":6.83,"lap_time":37.3,"turn_time":8.1,"straight_time":7.69},{"racer_boat_number":6,"ex_time":6.81,"lap_time":37.3,"turn_time":8.12,"straight_time":7.77}]},{"race_stadium_number":21,"race_number":4,"boats":[{"racer_boat_number":1,"ex_time":6.77,"lap_time":36.65,"turn_time":7.7,"straight_time":7.67},{"racer_boat_number":2,"ex_time":6.81,"lap_time":37.24,"turn_time":8.03,"straight_time":7.73},{"racer_boat_number":3,"ex_time":6.8,"lap_time":36.79,"turn_time":7.88,"straight_time":7.68},{"racer_boat_number":4,"ex_time":6.77,"lap_time":36.66,"turn_time":7.8,"straight_time":7.7},{"racer_boat_number":5,"ex_time":6.84,"lap_time":37.0,"turn_time":7.93,"straight_time":7.73},{"racer_boat_number":6,"ex_time":6.81,"lap_time":37.28,"turn_time":8.05,"straight_time":7.81}]},{"race_stadium_number":21,"race_number":5,"boats":[{"racer_boat_number":1,"ex_time":6.86,"lap_time":36.59,"turn_time":7.65,"straight_time":7.73},{"racer_boat_number":2,"ex_time":6.87,"lap_time":37.45,"turn_time":8.14,"straight_time":7.77},{"racer_boat_number":3,"ex_time":6.87,"lap_time":37.47,"turn_time":8.07,"straight_time":7.72},{"racer_boat_number":4,"ex_time":6.83,"lap_time":38.01,"turn_time":8.55,"straight_time":7.71},{"racer_boat_number":5,"ex_time":6.77,"lap_time":37.4,"turn_time":8.25,"straight_time":7.73},{"racer_boat_number":6,"ex_time":6.84,"lap_time":37.38,"turn_time":8.13,"straight_time":7.78}]},{"race_stadium_number":21,"race_number":6,"boats":[{"racer_boat_number":1,"ex_time":6.72,"lap_time":36.5,"turn_time":7.77,"straight_time":7.65},{"racer_boat_number":2,"ex_time":6.83,"lap_time":36.81,"turn_time":7.81,"straight_time":7.73},{"racer_boat_number":3,"ex_time":6.79,"lap_time":37.23,"turn_time":8.02,"straight_time":7.74},{"racer_boat_number":4,"ex_time":6.83,"lap_time":37.17,"turn_time":7.97,"straight_time":7.71},{"racer_boat_number":5,"ex_time":6.79,"lap_time":37.41,"turn_time":7.93,"straight_time":7.67},{"racer_boat_number":6,"ex_time":6.86,"lap_time":37.63,"turn_time":7.86,"straight_time":7.75}]},{"race_stadium_number":21,"race_number":7,"boats":[{"racer_boat_number":1,"ex_time":6.8,"lap_time":36.3,"turn_time":7.61,"straight_time":7.75},{"racer_boat_number":2,"ex_time":6.78,"lap_time":36.94,"turn_time":7.93,"straight_time":7.8},{"racer_boat_number":3,"ex_time":6.94,"lap_time":37.36,"turn_time":8.12,"straight_time":7.81},{"racer_boat_number":4,"ex_time":6.88,"lap_time":37.15,"turn_time":8.06,"straight_time":7.71},{"racer_boat_number":5,"ex_time":6.93,"lap_time":37.05,"turn_time":8.03,"straight_time":7.8},{"racer_boat_number":6,"ex_time":6.91,"lap_time":37.29,"turn_time":8.23,"straight_time":7.75}]},{"race_stadium_number":21,"race_number":8,"boats":[{"racer_boat_number":1,"ex_time":6.79,"lap_time":37.08,"turn_time":7.92,"straight_time":7.65},{"racer_boat_number":2,"ex_time":6.85,"lap_time":37.42,"turn_time":8.21,"straight_time":7.7},{"racer_boat_number":3,"ex_time":6.81,"lap_time":37.16,"turn_time":8.31,"straight_time":7.66},{"racer_boat_number":4,"ex_time":6.83,"lap_time":37.09,"turn_time":7.98,"straight_time":7.79},{"racer_boat_number":5,"ex_time":6.82,"lap_time":36.83,"turn_time":7.92,"straight_time":7.73},{"racer_boat_number":6,"ex_time":6.81,"lap_time":37.3,"turn_time":8.1,"straight_time":7.82}]},{"race_stadium_number":21,"race_number":9,"boats":[{"racer_boat_number":1,"ex_time":6.86,"lap_time":36.94,"turn_time":7.78,"straight_time":7.76},{"racer_boat_number":2,"ex_time":6.82,"lap_time":37.23,"turn_time":7.79,"straight_time":7.78},{"racer_boat_number":3,"ex_time":6.82,"lap_time":37.38,"turn_time":7.76,"straight_time":7.73},{"racer_boat_number":4,"ex_time":6.81,"lap_time":37.75,"turn_time":7.99,"straight_time":7.72},{"racer_boat_number":5,"ex_time":6.88,"lap_time":37.76,"turn_time":7.92,"straight_time":7.88},{"racer_boat_number":6,"ex_time":6.81,"lap_time":37.68,"turn_time":8.09,"straight_time":7.83}]}]}